clarifai/__init__.py
clarifai/cli.py
clarifai/errors.py
clarifai/versions.py
clarifai/cli/README.md
clarifai/cli/__init__.py
clarifai/cli/__main__.py
clarifai/cli/artifact.py
clarifai/cli/base.py
clarifai/cli/compute_cluster.py
clarifai/cli/deployment.py
clarifai/cli/model.py
clarifai/cli/nodepool.py
clarifai/cli/pipeline.py
clarifai/cli/pipeline_run.py
clarifai/cli/pipeline_step.py
clarifai/cli/pipeline_template.py
clarifai/cli/templates/__init__.py
clarifai/cli/templates/model_templates.py
clarifai/cli/templates/pipeline_step_templates.py
clarifai/cli/templates/pipeline_templates.py
clarifai/client/__init__.py
clarifai/client/app.py
clarifai/client/artifact.py
clarifai/client/artifact_version.py
clarifai/client/base.py
clarifai/client/compute_cluster.py
clarifai/client/dataset.py
clarifai/client/deployment.py
clarifai/client/input.py
clarifai/client/lister.py
clarifai/client/model.py
clarifai/client/model_client.py
clarifai/client/module.py
clarifai/client/nodepool.py
clarifai/client/pipeline.py
clarifai/client/pipeline_step.py
clarifai/client/runner.py
clarifai/client/search.py
clarifai/client/user.py
clarifai/client/workflow.py
clarifai/client/auth/__init__.py
clarifai/client/auth/helper.py
clarifai/client/auth/register.py
clarifai/client/auth/stub.py
clarifai/constants/artifact.py
clarifai/constants/base.py
clarifai/constants/dataset.py
clarifai/constants/input.py
clarifai/constants/model.py
clarifai/constants/rag.py
clarifai/constants/search.py
clarifai/constants/workflow.py
clarifai/datasets/__init__.py
clarifai/datasets/export/__init__.py
clarifai/datasets/export/inputs_annotations.py
clarifai/datasets/upload/__init__.py
clarifai/datasets/upload/base.py
clarifai/datasets/upload/features.py
clarifai/datasets/upload/image.py
clarifai/datasets/upload/multimodal.py
clarifai/datasets/upload/text.py
clarifai/datasets/upload/utils.py
clarifai/datasets/upload/loaders/README.md
clarifai/datasets/upload/loaders/__init__.py
clarifai-12.1.6.dist-info/licenses/LICENSE
clarifai-12.1.6.dist-info/METADATA
clarifai-12.1.6.dist-info/WHEEL
clarifai-12.1.6.dist-info/entry_points.txt
clarifai-12.1.6.dist-info/top_level.txt
clarifai-12.1.6.dist-info/RECORD
