Metadata-Version: 2.4
Name: clarifai
Version: 12.1.6
Home-page: https://github.com/Clarifai/clarifai-python
Author: Clarifai
Author-email: support@clarifai.com
License: Apache 2.0
Classifier: Topic :: Scientific/Engineering :: Artificial Intelligence
Classifier: Programming Language :: Python :: 3
Classifier: Programming Language :: Python :: 3 :: Only
Classifier: Programming Language :: Python :: 3.9
Classifier: Programming Language :: Python :: 3.10
Classifier: Programming Language :: Python :: 3.11
Classifier: Programming Language :: Python :: 3.12
Classifier: Programming Language :: Python :: Implementation :: CPython
Classifier: License :: OSI Approved :: Apache Software License
Classifier: Operating System :: OS Independent
Requires-Python: >=3.9
License-File: LICENSE
Requires-Dist: clarifai-grpc>=12.0.6
Requires-Dist: clarifai-protocol==0.0.35
Requires-Dist: numpy>=1.22.0
Requires-Dist: tqdm>=4.65.0
Requires-Dist: PyYAML>=6.0.1
Requires-Dist: schema==0.7.5
Requires-Dist: Pillow>=9.5.0
Requires-Dist: tabulate>=0.9.0
Requires-Dist: fsspec>=2024.6.1
Requires-Dist: click>=8.1.7
Requires-Dist: requests>=2.32.5
Requires-Dist: aiohttp>=3.10.0
Requires-Dist: uv==0.7.12
Requires-Dist: ruff==0.11.4
Requires-Dist: psutil==7.0.0
Requires-Dist: pygments>=2.19.2
Requires-Dist: pydantic_core>=2.33.2
Requires-Dist: packaging>=25.0
Requires-Dist: tenacity>=8.2.3
Requires-Dist: httpx>=0.27.0
Provides-Extra: all
Requires-Dist: pycocotools>=2.0.7; extra == "all"
Dynamic: author
Dynamic: author-email
Dynamic: classifier
Dynamic: description
Dynamic: description-content-type
Dynamic: home-page
Dynamic: license
Dynamic: license-file
Dynamic: provides-extra
Dynamic: requires-dist
Dynamic: requires-python
